btls/__init__.py
btls/mail.py
btls-0.0.2.dist-info/DESCRIPTION.rst
btls-0.0.2.dist-info/METADATA
btls-0.0.2.dist-info/RECORD
btls-0.0.2.dist-info/WHEEL
btls-0.0.2.dist-info/metadata.json
btls-0.0.2.dist-info/top_level.txt
