Metadata-Version: 2.0
Name: btls
Version: 0.0.2
Summary: brucezz's toolbox
Home-page: https://github.com/brucezz/btls
Author: Brucezz
Author-email: im.brucezz@gmail.com
License: MIT
Keywords: python tools
Platform: UNKNOWN
Requires-Dist: yagmail
